{
    "swagger": "2.0",
    "info": {
        "contact": {}
    },
    "paths": {
        "/api/billing/quota": {
            "get": {
                "produces": [
                    "application/json"
                ],
                "tags": [
                    "billing"
                ],
                "summary": "Get quota summary",
                "responses": {
                    "200": {
                        "description": "OK",
                        "schema": {
                            "$ref": "#/definitions/src_solsynth_dev_sosys_filesystem_internal_service.QuotaSummary"
                        }
                    }
                }
            }
        },
        "/api/billing/quota/records": {
            "get": {
                "produces": [
                    "application/json"
                ],
                "tags": [
                    "billing"
                ],
                "summary": "List quota records",
                "responses": {
                    "200": {
                        "description": "OK",
                        "schema": {
                            "type": "array",
                            "items": {
                                "$ref": "#/definitions/src_solsynth_dev_sosys_filesystem_internal_database.QuotaRecord"
                            }
                        }
                    }
                }
            }
        },
        "/api/billing/usage": {
            "get": {
                "produces": [
                    "application/json"
                ],
                "tags": [
                    "billing"
                ],
                "summary": "Get quota usage",
                "responses": {
                    "200": {
                        "description": "OK",
                        "schema": {
                            "$ref": "#/definitions/src_solsynth_dev_sosys_filesystem_internal_service.QuotaSummary"
                        }
                    }
                }
            }
        },
        "/api/billing/usage/{poolId}": {
            "get": {
                "produces": [
                    "application/json"
                ],
                "tags": [
                    "billing"
                ],
                "summary": "Get pool usage",
                "parameters": [
                    {
                        "type": "string",
                        "description": "Pool ID",
                        "name": "poolId",
                        "in": "path",
                        "required": true
                    }
                ],
                "responses": {
                    "200": {
                        "description": "OK",
                        "schema": {
                            "type": "object",
                            "additionalProperties": true
                        }
                    }
                }
            }
        },
        "/api/files/upload/complete/{taskId}": {
            "post": {
                "produces": [
                    "application/json"
                ],
                "tags": [
                    "uploads"
                ],
                "summary": "Complete upload",
                "parameters": [
                    {
                        "type": "string",
                        "description": "Task ID",
                        "name": "taskId",
                        "in": "path",
                        "required": true
                    }
                ],
                "responses": {
                    "200": {
                        "description": "OK",
                        "schema": {
                            "$ref": "#/definitions/src_solsynth_dev_sosys_filesystem_internal_database.CloudFile"
                        }
                    }
                }
            }
        },
        "/api/files/upload/create": {
            "post": {
                "consumes": [
                    "application/json"
                ],
                "produces": [
                    "application/json"
                ],
                "tags": [
                    "uploads"
                ],
                "summary": "Create upload task",
                "responses": {
                    "200": {
                        "description": "OK",
                        "schema": {
                            "type": "object",
                            "additionalProperties": true
                        }
                    }
                }
            }
        },
        "/api/files/upload/direct": {
            "post": {
                "produces": [
                    "application/json"
                ],
                "tags": [
                    "uploads"
                ],
                "summary": "Direct upload",
                "responses": {
                    "200": {
                        "description": "OK",
                        "schema": {
                            "$ref": "#/definitions/src_solsynth_dev_sosys_filesystem_internal_database.CloudFile"
                        }
                    }
                }
            }
        },
        "/api/files/{id}/info": {
            "get": {
                "produces": [
                    "application/json"
                ],
                "tags": [
                    "files"
                ],
                "summary": "Get file info",
                "parameters": [
                    {
                        "type": "string",
                        "description": "File ID",
                        "name": "id",
                        "in": "path",
                        "required": true
                    }
                ],
                "responses": {
                    "200": {
                        "description": "OK",
                        "schema": {
                            "$ref": "#/definitions/src_solsynth_dev_sosys_filesystem_internal_database.CloudFile"
                        }
                    },
                    "404": {
                        "description": "Not Found",
                        "schema": {
                            "type": "object",
                            "additionalProperties": true
                        }
                    }
                }
            }
        },
        "/api/files/{id}/open": {
            "get": {
                "produces": [
                    "application/json"
                ],
                "tags": [
                    "files"
                ],
                "summary": "Open file",
                "parameters": [
                    {
                        "type": "string",
                        "description": "File ID",
                        "name": "id",
                        "in": "path",
                        "required": true
                    },
                    {
                        "type": "boolean",
                        "description": "Download",
                        "name": "download",
                        "in": "query"
                    }
                ],
                "responses": {
                    "307": {
                        "description": "Temporary Redirect"
                    },
                    "404": {
                        "description": "Not Found",
                        "schema": {
                            "type": "object",
                            "additionalProperties": true
                        }
                    }
                }
            }
        }
    },
    "definitions": {
        "gorm.DeletedAt": {
            "type": "object",
            "properties": {
                "time": {
                    "type": "string"
                },
                "valid": {
                    "description": "Valid is true if Time is not NULL",
                    "type": "boolean"
                }
            }
        },
        "src_solsynth_dev_sosys_filesystem_internal_database.CloudFile": {
            "type": "object",
            "properties": {
                "account_id": {
                    "type": "string"
                },
                "application_type": {
                    "type": "string"
                },
                "children": {
                    "type": "array",
                    "items": {
                        "$ref": "#/definitions/src_solsynth_dev_sosys_filesystem_internal_database.CloudFile"
                    }
                },
                "created_at": {
                    "type": "string"
                },
                "deleted_at": {
                    "$ref": "#/definitions/gorm.DeletedAt"
                },
                "expired_at": {
                    "type": "string"
                },
                "file_meta": {
                    "type": "array",
                    "items": {
                        "type": "integer"
                    }
                },
                "id": {
                    "type": "string"
                },
                "indexed": {
                    "type": "boolean"
                },
                "is_folder": {
                    "type": "boolean"
                },
                "is_marked_recycle": {
                    "type": "boolean"
                },
                "name": {
                    "type": "string"
                },
                "object": {
                    "$ref": "#/definitions/src_solsynth_dev_sosys_filesystem_internal_database.FileObject"
                },
                "object_id": {
                    "type": "string"
                },
                "parent_id": {
                    "type": "string"
                },
                "storage_id": {
                    "type": "string"
                },
                "storage_key": {
                    "type": "string"
                },
                "storage_url": {
                    "type": "string"
                },
                "updated_at": {
                    "type": "string"
                },
                "uploaded_at": {
                    "type": "string"
                },
                "usage": {
                    "type": "string"
                },
                "user_meta": {
                    "type": "array",
                    "items": {
                        "type": "integer"
                    }
                }
            }
        },
        "src_solsynth_dev_sosys_filesystem_internal_database.FileObject": {
            "type": "object",
            "properties": {
                "created_at": {
                    "type": "string"
                },
                "has_compression": {
                    "type": "boolean"
                },
                "has_thumbnail": {
                    "type": "boolean"
                },
                "hash": {
                    "type": "string"
                },
                "id": {
                    "type": "string"
                },
                "meta": {
                    "type": "array",
                    "items": {
                        "type": "integer"
                    }
                },
                "mime_type": {
                    "type": "string"
                },
                "size": {
                    "type": "integer"
                },
                "storage_key": {
                    "type": "string"
                },
                "updated_at": {
                    "type": "string"
                }
            }
        },
        "src_solsynth_dev_sosys_filesystem_internal_database.QuotaRecord": {
            "type": "object",
            "properties": {
                "account_id": {
                    "type": "string"
                },
                "created_at": {
                    "type": "string"
                },
                "expired_at": {
                    "type": "string"
                },
                "id": {
                    "type": "string"
                },
                "name": {
                    "type": "string"
                },
                "quota": {
                    "type": "integer"
                },
                "updated_at": {
                    "type": "string"
                }
            }
        },
        "src_solsynth_dev_sosys_filesystem_internal_service.QuotaSummary": {
            "type": "object",
            "properties": {
                "based_quota": {
                    "type": "integer"
                },
                "extra_quota": {
                    "type": "integer"
                },
                "total_quota": {
                    "type": "integer"
                }
            }
        }
    }
}